setup.py
normalbinomialdistributions/Binomialdistribution.py
normalbinomialdistributions/Gaussiandistribution.py
normalbinomialdistributions/Generaldistribution.py
normalbinomialdistributions/__init__.py
normalbinomialdistributions.egg-info/PKG-INFO
normalbinomialdistributions.egg-info/SOURCES.txt
normalbinomialdistributions.egg-info/dependency_links.txt
normalbinomialdistributions.egg-info/not-zip-safe
normalbinomialdistributions.egg-info/top_level.txt